tjst/tests.py
tjst/tjst.js
tjst/__init__.py
tjst/tjst.py
tjst/bin/tjst-compile
tjst-0.1.0.dist-info/top_level.txt
tjst-0.1.0.dist-info/WHEEL
tjst-0.1.0.dist-info/DESCRIPTION.rst
tjst-0.1.0.dist-info/metadata.json
tjst-0.1.0.dist-info/METADATA
tjst-0.1.0.dist-info/RECORD
tjst-0.1.0.data/scripts/tjst-compile
