Metadata-Version: 2.0
Name: tjst
Version: 0.1.0
Summary: Tiny JavaScript Templating.
Home-page: https://bitbucket.org/dkuryakin/tjst
Author: David Kuryakin
Author-email: me@dkuryakin.com
License: mit
Download-URL: https://bitbucket.org/dkuryakin/tjst/get/master.tar.gz
Keywords: javascript,templates
Platform: any
Classifier: Development Status :: 4 - Beta
Classifier: Environment :: Web Environment
Classifier: Intended Audience :: Developers
Classifier: License :: OSI Approved :: MIT License
Classifier: Operating System :: OS Independent
Classifier: Programming Language :: Python
Classifier: Topic :: Internet :: WWW/HTTP
Classifier: Topic :: Software Development :: Libraries :: Python Modules
Requires-Dist: PyExecJS
